hexl/__init__.py
hexl/hex_functions.py
hexl/hexl.py
tests/__init__.py
tests/hex_functions.py
tests/hexl.py
tests/tests.py
hexl-1.0.dist-info/METADATA
hexl-1.0.dist-info/WHEEL
hexl-1.0.dist-info/top_level.txt
hexl-1.0.dist-info/RECORD
