Metadata-Version: 2.1
Name: hexl
Version: 1.0
Summary: Better work with hexadecimal numbers
Home-page: https://github.com/FelipPalermo/hexl
Author: Felipe Palermo
Author-email: felipeptavares06@gmail.com
Classifier: Programming Language :: Python :: 3
Classifier: License :: OSI Approved :: MIT License
Classifier: Operating System :: OS Independent
Requires-Python: >=3.6
